fastapi_maker/__init__.py
fastapi_maker/cli.py
fastapi_maker/generators/__init__.py
fastapi_maker/generators/audit_manager.py
fastapi_maker/generators/entity_generator.py
fastapi_maker/generators/migration_manager.py
fastapi_maker/generators/project_initializer.py
fastapi_maker/generators/relation_manager.py
fastapi_maker/generators/router_update.py
fastapi_maker/generators/ruff_config.py
fastapi_maker/templates/__init__.py
fastapi_maker/templates/entity_templates.py
fastapi_maker/templates/relation_templates.py
fastapi_maker/utils/code_editor.py
fastapi_maker/utils/dto_checker.py
fastapi_maker/utils/example_values.py
fastapi_maker/utils/line_locator.py
fastapi_maker/utils/pydantic_imports.py
fastapi_maker/utils/pydantic_type_map.py
fastapi_maker/utils/ruff_executor.py
fastapi_maker/utils/sqlalchemy_type_map.py
fastapi_maker-0.2.5.dist-info/licenses/LICENSE
fastapi_maker-0.2.5.dist-info/METADATA
fastapi_maker-0.2.5.dist-info/WHEEL
fastapi_maker-0.2.5.dist-info/entry_points.txt
fastapi_maker-0.2.5.dist-info/top_level.txt
fastapi_maker-0.2.5.dist-info/RECORD
