Metadata-Version: 2.4
Name: fastapi-maker
Version: 0.2.5
Summary: A CLI tool to scaffold FastAPI projects and modules (work in progress).
Author-email: Daryll Lorenzo Alfonso <daryllla77@gmail.com>
License-Expression: MIT
Project-URL: Homepage, https://github.com/DaryllLorenzo/fastapi-maker
Classifier: Programming Language :: Python :: 3
Classifier: Operating System :: OS Independent
Classifier: Environment :: Console
Classifier: Intended Audience :: Developers
Classifier: Topic :: Software Development :: Code Generators
Requires-Python: >=3.8
License-File: LICENSE
Requires-Dist: typer>=0.9.0
Requires-Dist: fastapi[standard]>=0.100.0
Requires-Dist: alembic>=1.10.0
Requires-Dist: python-dotenv>=1.0.0
Requires-Dist: fastapi-standalone-docs>=0.2.0
Requires-Dist: questionary>=2.1.1
Requires-Dist: ruff>=0.14.0
Requires-Dist: toml>=0.10.2
Requires-Dist: pip-audit>=2.0.0
Provides-Extra: dev
Requires-Dist: build; extra == "dev"
Requires-Dist: twine; extra == "dev"
Dynamic: license-file
